clusterservice/__init__.py
clusterservice/controllers/ClusterService.py
clusterservice/controllers/__init__.py
clusterservice/models/BaseGraphDatabase.py
clusterservice/models/__init__.py
clusterservice/models/neo4j_node_classes.py
clusterservice/services/AlbertQuestionAnswerer.py
clusterservice/services/ClusterBuilder.py
clusterservice/services/Embedder.py
clusterservice/services/GraphDbReaderWriter.py
clusterservice/services/Neo4jDatabase.py
clusterservice/services/__init__.py
clusterservice/utils/__init__.py
clusterservice/utils/squad_data_process.py
clusterservice-0.0.24.dist-info/METADATA
clusterservice-0.0.24.dist-info/WHEEL
clusterservice-0.0.24.dist-info/top_level.txt
clusterservice-0.0.24.dist-info/RECORD
